flex_config/__init__.py
flex_config/aws_source.py
flex_config/config_source.py
flex_config/env_source.py
flex_config/file_sources/__init__.py
flex_config/file_sources/file_source.py
flex_config/file_sources/json_source.py
flex_config/file_sources/toml_source.py
flex_config/file_sources/yaml_source.py
flex_config/py.typed
flex_config/utils.py
flex_config-3.0.0.dist-info/LICENSE
flex_config-3.0.0.dist-info/METADATA
flex_config-3.0.0.dist-info/WHEEL
flex_config-3.0.0.dist-info/RECORD
