Metadata-Version: 2.1
Name: flex-config
Version: 3.0.0
Summary: Easily configure Python apps via environment variables, YAML, and AWS SSM Param Store.
Home-page: https://github.com/emann/flex-config
License: MIT
Keywords: config,AWS,SSM,serverless,environment
Author: Dylan Anthony
Author-email: danthony@triaxtec.com
Requires-Python: >=3.10,<4.0
Classifier: Development Status :: 5 - Production/Stable
Classifier: Intended Audience :: Developers
Classifier: License :: OSI Approved :: MIT License
Classifier: Programming Language :: Python :: 3
Classifier: Programming Language :: Python :: 3.10
Classifier: Programming Language :: Python :: 3.11
Classifier: Topic :: Utilities
Provides-Extra: all
Provides-Extra: aws
Provides-Extra: toml
Provides-Extra: yaml
Requires-Dist: boto3 (>=1.13.1,<2.0.0) ; extra == "aws" or extra == "all"
Requires-Dist: pydantic (>=2.5.2,<3.0.0)
Requires-Dist: pyyaml (>=6.0.1,<7.0.0) ; extra == "yaml" or extra == "all"
Requires-Dist: toml (>=0.10.2,<0.11.0) ; extra == "toml" or extra == "all"
Project-URL: Documentation, https://emann.github.io/flex-config
Project-URL: Repository, https://github.com/emann/flex-config
